{
  "network_name": "Complex Distribution Network",
  "description": "A more complex network with multiple junctions and outlets",
  "nodes": [
    {
      "id": "inlet",
      "name": "Main Inlet",
      "elevation": 0.0,
      "type": "inlet",
      "x": 0.0,
      "y": 0.0
    },
    {
      "id": "junction1",
      "name": "Primary Junction",
      "elevation": 1.0,
      "type": "junction",
      "x": 10.0,
      "y": 0.0
    },
    {
      "id": "junction2",
      "name": "Secondary Junction A",
      "elevation": 2.0,
      "type": "junction",
      "x": 20.0,
      "y": 5.0
    },
    {
      "id": "junction3",
      "name": "Secondary Junction B",
      "elevation": 1.5,
      "type": "junction",
      "x": 20.0,
      "y": -5.0
    },
    {
      "id": "outlet1",
      "name": "Outlet 1A",
      "elevation": 2.5,
      "type": "outlet",
      "x": 30.0,
      "y": 8.0
    },
    {
      "id": "outlet2",
      "name": "Outlet 1B",
      "elevation": 2.0,
      "type": "outlet",
      "x": 30.0,
      "y": 2.0
    },
    {
      "id": "outlet3",
      "name": "Outlet 2A",
      "elevation": 1.8,
      "type": "outlet",
      "x": 30.0,
      "y": -2.0
    },
    {
      "id": "outlet4",
      "name": "Outlet 2B",
      "elevation": 1.2,
      "type": "outlet",
      "x": 30.0,
      "y": -8.0
    }
  ],
  "components": [
    {
      "id": "main_channel",
      "name": "Main Supply Channel",
      "type": "channel",
      "diameter": 0.10,
      "length": 10.0
    },
    {
      "id": "branch_a_channel",
      "name": "Branch A Channel",
      "type": "channel",
      "diameter": 0.06,
      "length": 12.0
    },
    {
      "id": "branch_b_channel",
      "name": "Branch B Channel",
      "type": "channel",
      "diameter": 0.06,
      "length": 12.0
    },
    {
      "id": "sub_branch_a1",
      "name": "Sub-branch A1",
      "type": "channel",
      "diameter": 0.04,
      "length": 8.0
    },
    {
      "id": "sub_branch_a2",
      "name": "Sub-branch A2",
      "type": "channel",
      "diameter": 0.04,
      "length": 6.0
    },
    {
      "id": "sub_branch_b1",
      "name": "Sub-branch B1",
      "type": "channel",
      "diameter": 0.04,
      "length": 7.0
    },
    {
      "id": "sub_branch_b2",
      "name": "Sub-branch B2",
      "type": "channel",
      "diameter": 0.04,
      "length": 9.0
    },
    {
      "id": "nozzle1",
      "name": "Nozzle 1A",
      "type": "nozzle",
      "diameter": 0.020,
      "nozzle_type": "venturi"
    },
    {
      "id": "nozzle2",
      "name": "Nozzle 1B",
      "type": "nozzle",
      "diameter": 0.025,
      "nozzle_type": "rounded"
    },
    {
      "id": "nozzle3",
      "name": "Nozzle 2A",
      "type": "nozzle",
      "diameter": 0.022,
      "nozzle_type": "sharp_edged"
    },
    {
      "id": "nozzle4",
      "name": "Nozzle 2B",
      "type": "nozzle",
      "diameter": 0.018,
      "nozzle_type": "flow_nozzle"
    }
  ],
  "connections": [
    {
      "from_node": "inlet",
      "to_node": "junction1",
      "component": "main_channel"
    },
    {
      "from_node": "junction1",
      "to_node": "junction2",
      "component": "branch_a_channel"
    },
    {
      "from_node": "junction1",
      "to_node": "junction3",
      "component": "branch_b_channel"
    },
    {
      "from_node": "junction2",
      "to_node": "outlet1",
      "component": "sub_branch_a1"
    },
    {
      "from_node": "junction2",
      "to_node": "outlet2",
      "component": "sub_branch_a2"
    },
    {
      "from_node": "junction3",
      "to_node": "outlet3",
      "component": "sub_branch_b1"
    },
    {
      "from_node": "junction3",
      "to_node": "outlet4",
      "component": "sub_branch_b2"
    }
  ],
  "simulation": {
    "flow_parameters": {
      "total_flow_rate": 0.025,
      "temperature": 45.0,
      "inlet_pressure": 250000.0,
      "outlet_pressure": null
    },
    "fluid_properties": {
      "oil_density": 900.0,
      "oil_type": "SAE40"
    },
    "solver_settings": {
      "max_iterations": 150,
      "tolerance": 1e-6,
      "relaxation_factor": 0.7
    },
    "output_settings": {
      "output_units": "metric",
      "detailed_output": true,
      "save_results": true,
      "results_file": "complex_network_results.json"
    }
  },
  "metadata": {
    "created_by": "manual",
    "version": "1.0",
    "notes": "Complex network with multiple levels of branching"
  }
}